{
  "actors": [
    {
      "type": "Actor",
      "name": "skybox",
      "persistent": true,
      "transform": {
        "position": [ 0, 0, 1 ],
        "scale": [ 1, 1, 1 ],
        "rotation": [ 0, 0, 0 ]
      },
      "components": [
        {
          "type": "ModelComponent",
          "modelName": "models/cube.obj",
          "materialName": "materials/skybox.mtrl",
          "enableDepth": false,
          "cullface": "front"
        }
      ]
    },
    {
      "type": "Actor",
      "name": "actor1",
      "persistent": true,
      "active": true,
      "enableDepth": false,
      "transform": {
        "position": [ -0.9, -0.6, 16.2 ],
        "scale": [ 0.1, 0.1, 0.1 ],
        "rotation": [ 0, 78, 0 ]
      },
      "components": [
        {
          "type": "ModelComponent",
          "modelName": "models/Gear1.obj",
          "materialName": "materials/gear1.mtrl"
        }
      ]
    },
    {
      "type": "Actor",
      "name": "actor2",
      "persistent": true,
      "active": true,
      "enableDepth": false,
      "transform": {
        "position": [ -1.5, -0.7, 17.8 ],
        "scale": [ 1, 1, 1 ],
        "rotation": [ 0, 90, -2 ]
      },
      "components": [
        {
          "type": "ModelComponent",
          "modelName": "models/bottles/glass_bottle.obj",
          "materialName": "materials/refraction.mtrl"
        }
      ]
    },
    {
      "type": "Actor",
      "name": "actor3",
      "persistent": true,
      "active": false,
      "enableDepth": false,
      "transform": {
        "position": [ 0.4, -0.3, 17.2 ],
        "scale": [ 0.002, 0.002, 0.002 ],
        "rotation": [ -3, 322, 0 ]
      },
      "components": [
        {
          "type": "ModelComponent",
          "modelName": "models/LionKeystone.obj",
          "materialName": "materials/lion.mtrl"
        }
      ]
    } 
  ]
}
